tsgd/__init__.py
tsgd/tsgd.py
tsgd-0.0.2.dist-info/LICENSE
tsgd-0.0.2.dist-info/METADATA
tsgd-0.0.2.dist-info/WHEEL
tsgd-0.0.2.dist-info/top_level.txt
tsgd-0.0.2.dist-info/RECORD
