Metadata-Version: 2.1
Name: tsgd
Version: 0.0.2
Summary: TSGD optimizer for Pytorch
Home-page: https://github.com/kunzeng/TSGD
Author: kun zeng
Author-email: zki@163.com
License: UNKNOWN
Platform: UNKNOWN
Classifier: Programming Language :: Python :: 3
Requires-Python: >=3.0
